gshogi/__init__.py
gshogi/board.py
gshogi/comments.py
gshogi/constants.py
gshogi/drag_and_drop.py
gshogi/engine_debug.py
gshogi/engine_manager.py
gshogi/engine_output.py
gshogi/gamelist.py
gshogi/gshogi.py
gshogi/gui.py
gshogi/gv.py
gshogi/load_save.py
gshogi/move_list.py
gshogi/pieces.py
gshogi/psn.py
gshogi/set_board_colours.py
gshogi/time_control.py
gshogi/usi.py
gshogi/utils.py
gshogi/engine.cpython-36m-i386-linux-gnu.so
gshogi/data/opening.bbk
gshogi/glade/comments.glade
gshogi/glade/common_engine_settings.glade
gshogi/glade/engine_debug.glade
gshogi/glade/engine_output.glade
gshogi/glade/gamelist.glade
gshogi/glade/main_window.glade
gshogi/glade/move_list.glade
gshogi/glade/preferences.glade
gshogi/glade/set_colours.glade
gshogi/glade/set_pieces.glade
gshogi/images/logo.png
gshogi/images/wood1.png
gshogi/images/wood1_hl.png
gshogi/images/eastern/bishopB.png
gshogi/images/eastern/bishopPB.png
gshogi/images/eastern/bishopPW.png
gshogi/images/eastern/bishopW.png
gshogi/images/eastern/goldB.png
gshogi/images/eastern/goldW.png
gshogi/images/eastern/kingB.png
gshogi/images/eastern/kingW.png
gshogi/images/eastern/knightB.png
gshogi/images/eastern/knightPB.png
gshogi/images/eastern/knightPW.png
gshogi/images/eastern/knightW.png
gshogi/images/eastern/lanceB.png
gshogi/images/eastern/lancePB.png
gshogi/images/eastern/lancePW.png
gshogi/images/eastern/lanceW.png
gshogi/images/eastern/pawnB.png
gshogi/images/eastern/pawnPB.png
gshogi/images/eastern/pawnPW.png
gshogi/images/eastern/pawnW.png
gshogi/images/eastern/rookB.png
gshogi/images/eastern/rookPB.png
gshogi/images/eastern/rookPW.png
gshogi/images/eastern/rookW.png
gshogi/images/eastern/silverB.png
gshogi/images/eastern/silverPB.png
gshogi/images/eastern/silverPW.png
gshogi/images/eastern/silverW.png
gshogi/images/gshogi/bishopB.png
gshogi/images/gshogi/bishopPB.png
gshogi/images/gshogi/goldB.png
gshogi/images/gshogi/kingB.png
gshogi-0.5.1.dist-info/DESCRIPTION.rst
gshogi-0.5.1.dist-info/entry_points.txt
gshogi-0.5.1.dist-info/metadata.json
gshogi-0.5.1.dist-info/top_level.txt
gshogi-0.5.1.dist-info/WHEEL
gshogi-0.5.1.dist-info/METADATA
gshogi-0.5.1.dist-info/RECORD
